grappelli_modeltranslation/__init__.py
grappelli_modeltranslation/admin.py
grappelli_modeltranslation/apps.py
grappelli_modeltranslation/static/grappelli_modeltranslation/css/tabbed_translation_fields.css
grappelli_modeltranslation/static/grappelli_modeltranslation/js/tabbed_translation_fields.js
grappelli_modeltranslation2-0.1.4.dist-info/METADATA
grappelli_modeltranslation2-0.1.4.dist-info/WHEEL
grappelli_modeltranslation2-0.1.4.dist-info/top_level.txt
grappelli_modeltranslation2-0.1.4.dist-info/RECORD
